openclip_service/__init__.py
openclip_service/clip_worker.py
openclip_service/service.py
openclip_service-0.1.1.dist-info/METADATA
openclip_service-0.1.1.dist-info/WHEEL
openclip_service-0.1.1.dist-info/entry_points.txt
openclip_service-0.1.1.dist-info/RECORD
